pickled_carrots/DPData.py
pickled_carrots/DPPlot.py
pickled_carrots/DPUtil.py
pickled_carrots/__init__.py
pickled_carrots/database.py
pickled_carrots/dataclass.py
pickled_carrots/mathutil.py
pickled_carrots/plot.py
pickled_carrots/resources/event_type_lookup.pickle
pickled_carrots/vinegar/__init__.py
pickled_carrots/vinegar/core.py
pickled_carrots/vinegar/event.py
pickled_carrots/vinegar/inventory.py
pickled_carrots/vinegar/tests/test_read_hsf.py
pickled_carrots/waveforms.py
pickled_carrots-1.0.15.dist-info/METADATA
pickled_carrots-1.0.15.dist-info/WHEEL
pickled_carrots-1.0.15.dist-info/RECORD
