Metadata-Version: 2.1
Name: pickled-carrots
Version: 1.0.15
Summary: 
Author: pickled cattots team
Requires-Python: >=3.9,<4.0
Classifier: Programming Language :: Python :: 3
Classifier: Programming Language :: Python :: 3.9
Classifier: Programming Language :: Python :: 3.10
Classifier: Programming Language :: Python :: 3.11
Requires-Dist: SQLAlchemy (>=2.0.13,<3.0.0)
Requires-Dist: boto3 (>=1.26.128,<2.0.0)
Requires-Dist: certifi (>=2022.12.7,<2023.0.0)
Requires-Dist: cryptography (>=40.0.2,<41.0.0)
Requires-Dist: h5py (>=3.8.0,<4.0.0)
Requires-Dist: ipdb (>=0.13.13,<0.14.0)
Requires-Dist: jupyter (>=1.0.0,<2.0.0)
Requires-Dist: mplstereonet (>=0.6.2,<0.7.0)
Requires-Dist: plotly (>=5.14.1,<6.0.0)
Requires-Dist: psutil (>=5.9.5,<6.0.0)
Requires-Dist: pymongo (>=4.3.3,<5.0.0)
Requires-Dist: pyodbc (==4.0.34)
Requires-Dist: pyproj (==3.4.1)
Requires-Dist: python-ternary (>=1.0.8,<2.0.0)
Requires-Dist: pytz (>=2023.3,<2024.0)
Requires-Dist: shapely (>=2.0.1,<3.0.0)
Requires-Dist: statsmodels (>=0.14.0,<0.15.0)
Requires-Dist: uquake (>=1.4.8,<2.0.0)
